setup.py
preach/__init__.py
preach/compile.py
preach/note.py
preach/watch.py
preach.egg-info/PKG-INFO
preach.egg-info/SOURCES.txt
preach.egg-info/dependency_links.txt
preach.egg-info/entry_points.txt
preach.egg-info/requires.txt
preach.egg-info/top_level.txt