Metadata-Version: 1.0
Name: preach
Version: 0.0.1
Summary: simple presentation builder
Home-page: https://github.com/frnsys/preach
Author: Francis Tseng
Author-email: f@frnsys.com
License: GPLv3
Platform: UNKNOWN
